setup.py
tamarin/__init__.py
tamarin/admin.py
tamarin/log_puller.py
tamarin/models.py
tamarin/parser.py
tamarin/tasks.py
tamarin.egg-info/PKG-INFO
tamarin.egg-info/SOURCES.txt
tamarin.egg-info/dependency_links.txt
tamarin.egg-info/requires.txt
tamarin.egg-info/top_level.txt
tamarin/management/__init__.py
tamarin/management/commands/__init__.py
tamarin/management/commands/tamarin_pull_logs.py
tamarin/migrations/0001_initial.py
tamarin/migrations/0002_auto__add_field_s3logrecord_request_method.py
tamarin/migrations/0003_auto__add_field_s3logrecord_http_version.py
tamarin/migrations/0004_auto__add_unique_s3logrecord_request_id.py
tamarin/migrations/0005_auto__chg_field_s3logrecord_total_time__chg_field_s3logrecord_turnarou.py
tamarin/migrations/0006_auto__chg_field_s3logrecord_turnaround_time.py
tamarin/migrations/0007_auto__chg_field_s3logrecord_object_size.py
tamarin/migrations/0008_auto__chg_field_s3logrecord_bytes_sent.py
tamarin/migrations/0009_auto__chg_field_s3logrecord_total_time.py
tamarin/migrations/0010_auto__chg_field_s3logrecord_referrer__chg_field_s3logrecord_requester_.py
tamarin/migrations/0011_auto__chg_field_s3logrecord_user_agent.py
tamarin/migrations/0012_auto__chg_field_s3logrecord_request_method.py
tamarin/migrations/0013_auto__chg_field_s3logrecord_http_version.py
tamarin/migrations/__init__.py