Metadata-Version: 1.0
Name: tamarin
Version: 0.1
Summary: A Django app for monitoring AWS usage in Django's admin.
Home-page: https://github.com/duointeractive/tamarin/
Author: Gregory Taylor
Author-email: gtaylor@duointeractive.com
License: BSD
Platform: any
Classifier: Development Status :: 3 - Alpha
Classifier: Intended Audience :: Developers
Classifier: License :: OSI Approved :: BSD License
Classifier: Operating System :: OS Independent
Classifier: Programming Language :: Python
Classifier: Topic :: Software Development :: Libraries :: Python Modules
Classifier: Framework :: Django
